LatentSemanticAnalyzer/DataLoaders.py
LatentSemanticAnalyzer/DocumentTermMatrixConstruction.py
LatentSemanticAnalyzer/LatentSemanticAnalyzer.py
LatentSemanticAnalyzer/__init__.py
LatentSemanticAnalyzer/resources/dfAbstracts.csv.gz
latentsemanticanalyzer-0.2.1.dist-info/licenses/LICENSE
latentsemanticanalyzer-0.2.1.dist-info/METADATA
latentsemanticanalyzer-0.2.1.dist-info/WHEEL
latentsemanticanalyzer-0.2.1.dist-info/top_level.txt
latentsemanticanalyzer-0.2.1.dist-info/RECORD
