Metadata-Version: 2.4
Name: LatentSemanticAnalyzer
Version: 0.2.1
Summary: Latent Semantic Analysis package based on "the standard" Latent Semantic Indexing theory.
Home-page: https://github.com/antononcube/Python-packages/tree/main/LatentSemanticAnalyzer
Author: Anton Antonov
Author-email: antononcube@posteo.net
Keywords: sparse,matrix,sparse matrix,linear algebra,linear,algebra,lsi,latent semantic indexing,dimension,reduction,dimension reduction,svd,singular value decomposition,nnmf,nmf,non-negative matrix factorization
Classifier: Programming Language :: Python :: 3
Classifier: License :: OSI Approved :: GNU General Public License v3 (GPLv3)
Classifier: Operating System :: OS Independent
Requires-Python: >=3.7
License-File: LICENSE
Requires-Dist: numpy
Requires-Dist: scipy
Requires-Dist: pandas
Requires-Dist: stop-words
Requires-Dist: snowballstemmer
Requires-Dist: nimfa
Requires-Dist: scikit-learn
Requires-Dist: SSparseMatrix
Requires-Dist: SparseMatrixRecommender
Dynamic: author
Dynamic: author-email
Dynamic: classifier
Dynamic: description
Dynamic: description-content-type
Dynamic: home-page
Dynamic: keywords
Dynamic: license-file
Dynamic: requires-dist
Dynamic: requires-python
Dynamic: summary
